{"favorite_id": 10417, "calc_type": "calculator", "dosing": false, "full_title_en": "Hurt, Insult, Threaten, Scream (HITS) Score", "short_title_en": "HITS", "medium_description_en": "Detects domestic abuse (intimate partner violence) in women and men in healthcare settings.", "short_description_en": "Detects domestic abuse in healthcare settings.", "before_use": "", "instructions_en": "", "slug": "hurt-insult-threaten-scream-hits-score", "logic_language": "javascript", "md5": "b88cd5fff592e1990a4f2fea60fb21dc", "cmeVersion": null, "cmeReleaseDate": null, "cmeEndDate": null, "cmeLastReviewed": null, "publishedAt": "2022-05-11T18:25:27.141Z", "vuid": "eabf659a-e71f-4fca-b781-e28b75ac34ae", "versionNumber": 1, "isVisibleInListView": true, "disabled": false, "replacement_calc_id": null, "disabled_reason": null, "search_abbreviation_en": ["Hurt, Insult, Threaten, Scream (HITS) Score", "HITS", "IPV", "intimate partner violence", "abuse", "abuse screening", "abuse screening tool", "domestic abuse", "domestic abuse screening", "domestic violence", "domestic violence screening"], "seo": {"meta_description_en": "The Hurt, Insult, Threaten, Scream (HITS) Score detects domestic abuse (intimate partner violence) in women and men in healthcare settings.", "keywords_en": "Hurt, Insult, Threaten, Scream (HITS) Score, HITS, IPV, intimate partner violence, abuse, abuse screening, abuse screening tool, domestic abuse, domestic abuse screening, domestic violence, domestic violence screening"}, "content": {"reviewer": {"expert_name": []}, "related_resources": {"mdcalc_rating": [], "guidelines": [], "teaching": [], "videos": [], "interests": [], "partner_contact": [], "sdm_tool": []}, "how_to_use": {"use_case_en": "<p>Do you use the Hurt, Insult, Threaten, Scream (HITS) Score and want to contribute your expertise?&nbsp;<a href=\"https://www.mdcalc.com/join-us\" target=\"_blank\" rel=\"noopener\">Join</a>&nbsp;our contributor team!</p>", "pearls_pitfalls_en": "", "why_use_en": ""}, "next_steps": {"advice_en": "<p>Do you use the Hurt, Insult, Threaten, Scream (HITS) Score and want to contribute your expertise?&nbsp;<a href=\"https://www.mdcalc.com/join-us\" target=\"_blank\" rel=\"noopener\">Join</a>&nbsp;our contributor team!</p>", "management_en": "", "critical_actions_en": ""}, "about": {"formula_en": "<p dir=\"ltr\">The HITS Score is calculated by the addition of the selected points:</p>\n<div dir=\"ltr\" align=\"left\">\n<table style=\"width: 100%;\"><colgroup><col style=\"width: 48.80546075085324%;\"><col style=\"width: 33.78839590443686%;\"><col style=\"width: 17.235494880546078%;\"></colgroup>\n<tbody>\n<tr>\n<td colspan=\"2\">\n<p dir=\"ltr\"><strong>Variable</strong></p>\n</td>\n<td>\n<p dir=\"ltr\"><strong>Points</strong></p>\n</td>\n</tr>\n<tr>\n<td rowspan=\"5\">\n<p dir=\"ltr\">How often does your partner physically <span style=\"text-decoration: underline;\">hurt</span> you?</p>\n</td>\n<td>\n<p dir=\"ltr\">Never</p>\n</td>\n<td>\n<p dir=\"ltr\">1</p>\n</td>\n</tr>\n<tr>\n<td>\n<p dir=\"ltr\">Rarely</p>\n</td>\n<td>\n<p dir=\"ltr\">2</p>\n</td>\n</tr>\n<tr>\n<td>\n<p dir=\"ltr\">Sometimes</p>\n</td>\n<td>\n<p dir=\"ltr\">3</p>\n</td>\n</tr>\n<tr>\n<td>\n<p dir=\"ltr\">Fairly often</p>\n</td>\n<td>\n<p dir=\"ltr\">4</p>\n</td>\n</tr>\n<tr>\n<td>\n<p dir=\"ltr\">Frequently</p>\n</td>\n<td>\n<p dir=\"ltr\">5</p>\n</td>\n</tr>\n<tr>\n<td rowspan=\"5\">\n<p dir=\"ltr\">How often does your partner <span style=\"text-decoration: underline;\">insult</span> you or talk down to you?</p>\n</td>\n<td>\n<p dir=\"ltr\">Never</p>\n</td>\n<td>\n<p dir=\"ltr\">1</p>\n</td>\n</tr>\n<tr>\n<td>\n<p dir=\"ltr\">Rarely</p>\n</td>\n<td>\n<p dir=\"ltr\">2</p>\n</td>\n</tr>\n<tr>\n<td>\n<p dir=\"ltr\">Sometimes</p>\n</td>\n<td>\n<p dir=\"ltr\">3</p>\n</td>\n</tr>\n<tr>\n<td>\n<p dir=\"ltr\">Fairly often</p>\n</td>\n<td>\n<p dir=\"ltr\">4</p>\n</td>\n</tr>\n<tr>\n<td>\n<p dir=\"ltr\">Frequently</p>\n</td>\n<td>\n<p dir=\"ltr\">5</p>\n</td>\n</tr>\n<tr>\n<td rowspan=\"5\">\n<p dir=\"ltr\">How often does your partner <span style=\"text-decoration: underline;\">threaten</span> you with harm?</p>\n</td>\n<td>\n<p dir=\"ltr\">Never</p>\n</td>\n<td>\n<p dir=\"ltr\">1</p>\n</td>\n</tr>\n<tr>\n<td>\n<p dir=\"ltr\">Rarely</p>\n</td>\n<td>\n<p dir=\"ltr\">2</p>\n</td>\n</tr>\n<tr>\n<td>\n<p dir=\"ltr\">Sometimes</p>\n</td>\n<td>\n<p dir=\"ltr\">3</p>\n</td>\n</tr>\n<tr>\n<td>\n<p dir=\"ltr\">Fairly often</p>\n</td>\n<td>\n<p dir=\"ltr\">4</p>\n</td>\n</tr>\n<tr>\n<td>\n<p dir=\"ltr\">Frequently</p>\n</td>\n<td>\n<p dir=\"ltr\">5</p>\n</td>\n</tr>\n<tr>\n<td rowspan=\"5\">\n<p dir=\"ltr\">How often does your partner <span style=\"text-decoration: underline;\">scream</span> or curse at you?</p>\n</td>\n<td>\n<p dir=\"ltr\">Never</p>\n</td>\n<td>\n<p dir=\"ltr\">1</p>\n</td>\n</tr>\n<tr>\n<td>\n<p dir=\"ltr\">Rarely</p>\n</td>\n<td>\n<p dir=\"ltr\">2</p>\n</td>\n</tr>\n<tr>\n<td>\n<p dir=\"ltr\">Sometimes</p>\n</td>\n<td>\n<p dir=\"ltr\">3</p>\n</td>\n</tr>\n<tr>\n<td>\n<p dir=\"ltr\">Fairly often</p>\n</td>\n<td>\n<p dir=\"ltr\">4</p>\n</td>\n</tr>\n<tr>\n<td>\n<p dir=\"ltr\">Frequently</p>\n</td>\n<td>\n<p dir=\"ltr\">5</p>\n</td>\n</tr>\n</tbody>\n</table>\n</div>\n<p>&nbsp;</p>", "more_info_en": "<p dir=\"ltr\">Interpretation:</p>\n<div dir=\"ltr\" align=\"left\">\n<table style=\"width: 56.484641638225256%;\"><colgroup><col style=\"width: 48.54368932038835%;\"><col style=\"width: 51.1326860841424%;\"></colgroup>\n<tbody>\n<tr>\n<td>\n<p dir=\"ltr\"><strong>HITS Score</strong></p>\n</td>\n<td>\n<p dir=\"ltr\"><strong>Screening Result</strong></p>\n</td>\n</tr>\n<tr>\n<td>\n<p dir=\"ltr\">&le;10</p>\n</td>\n<td>\n<p dir=\"ltr\">Negative</p>\n</td>\n</tr>\n<tr>\n<td>\n<p dir=\"ltr\">&gt;10</p>\n</td>\n<td>\n<p dir=\"ltr\">Positive</p>\n</td>\n</tr>\n</tbody>\n</table>\n</div>\n<p>&nbsp;</p>", "evidence_based_medicine_en": "", "references_list": {"Validation": [{"text": "Shakil A, Donald S, Sinacore JM, Krepcho M. Validation of the HITS domestic violence screening tool with males. Fam Med. 2005;37(3):193-198.", "href": "https://pubmed.ncbi.nlm.nih.gov/15739135/"}, {"text": "Feltner C, Wallace I, Berkman N, et al. Screening for intimate partner violence, elder abuse, and abuse of vulnerable adults: evidence report and systematic review for the US preventive services task force. JAMA. 2018;320(16):1688.", "href": "https://jamanetwork.com/journals/jama/fullarticle/2708120"}], "Outcomes": [], "Validations": [], "Original/Primary Reference": [{"text": "Sherin KM, Sinacore JM, Li XQ, Zitter RE, Shakil A. HITS: a short domestic violence screening tool for use in a family practice setting. Fam Med. 1998;30(7):508-512.", "href": "https://pubmed.ncbi.nlm.nih.gov/9669164/"}], "Other References": [], "Clinical Practice Guidelines": [], "Manufacturer Website": []}}, "creator": [{"qa_en": null, "approved": null, "name": "Dr. Kevin M. Sherin", "creator_info": {"deceased": null, "about_en": "<p><span>Kevin M. Sherin, MD, is a clinical professor of family medicine at Florida State University College of Medicine in Orlando, FL. He was aware the American College of Preventive Medicine Distinguished Service Award in Chicago in 2018. Dr. Sherin&rsquo;s primary research is focused on preventive healthcare and family medicine.</span></p>", "photo_en": "https://cdn-web-img.mdcalc.com/people/dr-kevin-m-sherin.jpg"}}], "contributor": {"expert_name": []}}, "input_schema": [{"type": "radio", "label_en": "<p>How often does your partner physically <span style=\"text-decoration: underline;\">hurt</span> you?</p>", "name": "hurt", "default": 0, "show_points": true, "optional": false, "conditionality": null, "tips_en": "", "options": [{"label": "Never", "value": 1}, {"label": "Rarely", "value": 2}, {"label": "Sometimes", "value": 3}, {"label": "Fairly often", "value": 4}, {"label": "Frequently", "value": 5}]}, {"type": "radio", "label_en": "<p>How often does your partner <span style=\"text-decoration: underline;\">insult</span> you or talk down to you?</p>", "name": "insult", "default": 0, "show_points": true, "optional": false, "conditionality": null, "tips_en": "", "options": [{"label": "Never", "value": 1}, {"label": "Rarely", "value": 2}, {"label": "Sometimes", "value": 3}, {"label": "Fairly often", "value": 4}, {"label": "Frequently", "value": 5}]}, {"type": "radio", "label_en": "<p>How often does your partner <span style=\"text-decoration: underline;\">threaten</span> you with harm?</p>", "name": "threaten", "default": 0, "show_points": true, "optional": false, "conditionality": null, "tips_en": "", "options": [{"label": "Never", "value": 1}, {"label": "Rarely", "value": 2}, {"label": "Sometimes", "value": 3}, {"label": "Fairly often", "value": 4}, {"label": "Frequently", "value": 5}]}, {"type": "radio", "label_en": "<p>How often does your partner <span style=\"text-decoration: underline;\">scream</span> or curse at you?</p>", "name": "scream", "default": 0, "show_points": true, "optional": false, "conditionality": null, "tips_en": "", "options": [{"label": "Never", "value": 1}, {"label": "Rarely", "value": 2}, {"label": "Sometimes", "value": 3}, {"label": "Fairly often", "value": 4}, {"label": "Frequently", "value": 5}]}], "chief_complaint_en": ["Agitation", "Altered Mental Status", "Anxious", "Depressed", "Injury/Trauma", "Loss of Appetite", "Preventive Care/Screening", "Suicidal", "Weight Loss/Gain"], "specialty_en": ["Critical Care", "Emergency Medicine", "Family Practice", "Hospitalist Medicine", "Internal Medicine", "OB-Gyn"], "purpose_en": ["Prognosis"], "system_en": ["Any/All"], "disease_en": ["Public Health"], "tags": [], "versions": [], "related_calcs": [{"calcId": 10418, "short_title_en": "OVAT", "slug": "ongoing-violence-assessment-tool-ovat"}, {"calcId": 10419, "short_title_en": "AAS", "slug": "abuse-assessment-screen-aas"}, {"calcId": 10396, "short_title_en": "WAST", "slug": "woman-abuse-screening-tool-wast"}]}