{
  "header": {
    "type": "elink",
    "version": "0.3"
  },
  "linksets": [
    {
      "dbfrom": "pubmed",
      "idurllist": [
        {
          "id": "20603345",
          "objurls": [
            {
              "url": {
                "value": "http://www.cmaj.ca/cgi/pmidlookup?view=long&pmid=20603345"
              },
              "iconurl": {
                "value": "/corehtml/query/egifs/http:--highwire.stanford.edu-icons-externalservices-pubmed-cmaj_free.gif"
              },
              "subjecttypes": [],
              "categories": [
                "Full Text Sources"
              ],
              "attributes": [
                "free resource"
              ],
              "provider": {
                "name": "HighWire",
                "nameabbr": "HighWire",
                "id": "3051"
              }
            },
            {
              "url": {
                "value": "https://www.ncbi.nlm.nih.gov/pmc/articles/pmid/20603345/"
              },
              "iconurl": {
                "value": "/corehtml/query/egifs/https:--www.ncbi.nlm.nih.gov-corehtml-pmc-pmcgifs-pubmed-pmc.png"
              },
              "subjecttypes": [],
              "categories": [
                "Full Text Sources"
              ],
              "attributes": [
                "free resource"
              ],
              "provider": {
                "name": "PubMed Central",
                "nameabbr": "PMC",
                "id": "3494"
              }
            }
          ]
        }
      ]
    }
  ]
}