{
  "header": {
    "type": "esummary",
    "version": "0.3"
  },
  "result": {
    "uids": [
      "6102236"
    ],
    "6102236": {
      "uid": "6102236",
      "pubdate": "1980 Mar 8",
      "epubdate": "",
      "source": "Lancet",
      "authors": [
        {
          "name": "Harvey RF",
          "authtype": "Author",
          "clusterid": ""
        },
        {
          "name": "Bradshaw JM",
          "authtype": "Author",
          "clusterid": ""
        }
      ],
      "lastauthor": "Bradshaw JM",
      "title": "A simple index of Crohn's-disease activity.",
      "sorttitle": "simple index of crohn s disease activity",
      "volume": "1",
      "issue": "8167",
      "pages": "514",
      "lang": [
        "eng"
      ],
      "nlmuniqueid": "2985213R",
      "issn": "0140-6736",
      "essn": "",
      "pubtype": [
        "Clinical Trial",
        "Journal Article"
      ],
      "recordstatus": "PubMed - indexed for MEDLINE",
      "pubstatus": "4",
      "articleids": [
        {
          "idtype": "pubmed",
          "idtypen": 1,
          "value": "6102236"
        },
        {
          "idtype": "doi",
          "idtypen": 3,
          "value": "10.1016/s0140-6736(80)92767-1"
        },
        {
          "idtype": "pii",
          "idtypen": 4,
          "value": "S0140-6736(80)92767-1"
        }
      ],
      "history": [
        {
          "pubstatus": "pubmed",
          "date": "1980/03/08 00:00"
        },
        {
          "pubstatus": "medline",
          "date": "1980/03/08 00:01"
        },
        {
          "pubstatus": "entrez",
          "date": "1980/03/08 00:00"
        }
      ],
      "references": [],
      "attributes": [],
      "pmcrefcount": "",
      "fulljournalname": "Lancet (London, England)",
      "elocationid": "",
      "doctype": "citation",
      "srccontriblist": [],
      "booktitle": "",
      "medium": "",
      "edition": "",
      "publisherlocation": "",
      "publishername": "",
      "srcdate": "",
      "reportnumber": "",
      "availablefromurl": "",
      "locationlabel": "",
      "doccontriblist": [],
      "docdate": "",
      "bookname": "",
      "chapter": "",
      "sortpubdate": "1980/03/08 00:00",
      "sortfirstauthor": "Harvey RF",
      "vernaculartitle": ""
    }
  }
}